<?xml version="1.0" encoding="utf-8" ?>
<dwsync>
<file name="back.png" server="C:/xampp/htdocs/" local="131331277090501660" remote="131331277090000000" Dst="1" />
<file name="camera.cpp" server="C:/xampp/htdocs/" local="131331277090506693" remote="131331277090000000" Dst="1" />
<file name="camera.h" server="C:/xampp/htdocs/" local="131331277090511668" remote="131331277090000000" Dst="1" />
<file name="CaptureWidget.qml" server="C:/xampp/htdocs/" local="131331277090521674" remote="131331277090000000" Dst="1" />
<file name="shoot.png" server="C:/xampp/htdocs/" local="131331277090526679" remote="131331277090000000" Dst="1" />
<file name="toolbar-left.png" server="C:/xampp/htdocs/" local="131331277090531688" remote="131331277090000000" Dst="1" />
<file name="toolbar-middle.png" server="C:/xampp/htdocs/" local="131331277090541693" remote="131331277090000000" Dst="1" />
<file name="toolbar-right.png" server="C:/xampp/htdocs/" local="131331277090546698" remote="131331277090000000" Dst="1" />
</dwsync>